notebook2md/__init__.py
notebook2md/converter.py
tests/__init__.py
tests/test_converter.py
notebook2md-0.1.0.dist-info/LICENSE
notebook2md-0.1.0.dist-info/METADATA
notebook2md-0.1.0.dist-info/WHEEL
notebook2md-0.1.0.dist-info/entry_points.txt
notebook2md-0.1.0.dist-info/top_level.txt
notebook2md-0.1.0.dist-info/RECORD
