Metadata-Version: 2.1
Name: notebook2md
Version: 0.1.0
Summary: A package to convert Jupyter notebooks to Markdown files
Home-page: https://github.com/shpetimhaxhiu/notebook2md
Author: Shpetim Haxhiu
Author-email: shpetim.h@gmail.com
Classifier: Programming Language :: Python :: 3
Classifier: License :: OSI Approved :: MIT License
Classifier: Operating System :: OS Independent
Requires-Python: >=3.6
License-File: LICENSE
Requires-Dist: nbformat
Requires-Dist: nbconvert
